pytranscript.py
pytranscript-0.3.0.dist-info/LICENSE
pytranscript-0.3.0.dist-info/METADATA
pytranscript-0.3.0.dist-info/WHEEL
pytranscript-0.3.0.dist-info/entry_points.txt
pytranscript-0.3.0.dist-info/top_level.txt
pytranscript-0.3.0.dist-info/RECORD
