Metadata-Version: 2.1
Name: pytranscript
Version: 0.3.0
Summary: CLI to transcript and translate audio and video files
Author-email: arnaud-ma <arnaudma.code@gmail.com>
License: MIT License
Project-URL: Documentation, https://github.com/arnaud-ma/pytranscript#readme
Project-URL: Repository, https://github.com/arnaud-ma/pytranscript
Project-URL: Source, https://github.com/arnaud-ma/pytranscript
Project-URL: Issues, https://github.com/arnaud-ma/pytranscript/issues
Keywords: transcript,translation,audio,video,subtitles
Classifier: License :: OSI Approved :: MIT License
Classifier: Programming Language :: Python :: 3
Classifier: Programming Language :: Python :: 3.12
Requires-Python: >=3.12
License-File: LICENSE
Requires-Dist: deep-translator >=1.11.4
Requires-Dist: tqdm >=4.66.1
Requires-Dist: vosk >=0.3.45
Requires-Dist: ffmpeg-python >=0.2.0
Requires-Dist: typed-argument-parser >=1.9.0
Provides-Extra: test
Requires-Dist: hypothesis >=6.92 ; extra == 'test'
